LICENSE
MANIFEST.in
README.rst
setup.cfg
setup.py
githubbot/__init__.py
githubbot/__main__.py
githubbot/configFile.cfg
githubbot/githubbot.py
githubbot/webconfig.cfg
githubbot.egg-info/PKG-INFO
githubbot.egg-info/SOURCES.txt
githubbot.egg-info/dependency_links.txt
githubbot.egg-info/entry_points.txt
githubbot.egg-info/not-zip-safe
githubbot.egg-info/requires.txt
githubbot.egg-info/top_level.txt
githubbot/static/style.css
githubbot/templates/index.html