Metadata-Version: 1.1
Name: githubbot
Version: 0.4.2
Summary: Automatically labels repositories' issues or pull requests on GitHub.
Home-page: https://github.com/tomanj23/githubBot
Author: Jakub Tomanek
Author-email: tomanj23@fit.cvut.cz
License: Public Domain
Platform: UNKNOWN
Classifier: Intended Audience :: Developers
Classifier: License :: Public Domain
Classifier: Programming Language :: Python :: 3
Classifier: Topic :: Software Development :: Version Control
